[
    {
        "name": "3D",
        "image1": "",
        "image2": "",
        "image3": "",
        "image4": ""
    },
    {
        "name": "Abstract",
        "image1": "",
        "image2": "",
        "image3": "",
        "image4": ""
    },
    {
        "name": "Aircraft",
        "image1": "",
        "image2": "",
        "image3": "",
        "image4": ""
    },
    {
        "name": "Amoled",
        "image1": "",
        "image2": "",
        "image3": "",
        "image4": ""
    },
    {
        "name": "Animal & Bird",
        "image1": "",
        "image2": "",
        "image3": "",
        "image4": ""
    },
    {
        "name": "Anime",
        "image1": "",
        "image2": "",
        "image3": "",
        "image4": ""
    },
    {
        "name": "Architecture",
        "image1": "",
        "image2": "",
        "image3": "",
        "image4": ""
    },
    {
        "name": "Art",
        "image1": "",
        "image2": "",
        "image3": "",
        "image4": ""
    },
    {
        "name": "Babies",
        "image1": "",
        "image2": "",
        "image3": "",
        "image4": ""
    },
    {
        "name": "Boken",
        "image1": "",
        "image2": "",
        "image3": "",
        "image4": ""
    },
    {
        "name": "Candle",
        "image1": "",
        "image2": "",
        "image3": "",
        "image4": ""
    },
    {
        "name": "Cartoon",
        "image1": "",
        "image2": "",
        "image3": "",
        "image4": ""
    },
    {
        "name": "Flowers",
        "image1": "",
        "image2": "",
        "image3": "",
        "image4": ""
    },
    {
        "name": "Food",
        "image1": "",
        "image2": "",
        "image3": "",
        "image4": ""
    },
    {
        "name": "Game",
        "image1": "",
        "image2": "",
        "image3": "",
        "image4": ""
    },
    {
        "name": "Girl",
        "image1": "",
        "image2": "",
        "image3": "",
        "image4": ""
    },
    {
        "name": "Kawaii",
        "image1": "",
        "image2": "",
        "image3": "",
        "image4": ""
    },
    {
        "name": "Love",
        "image1": "",
        "image2": "",
        "image3": "",
        "image4": ""
    },
    {
        "name": "Macro",
        "id_start": 851,
        "id_end": 900
    },
    {
        "name": "Mask",
        "image1": "",
        "image2": "",
        "image3": "",
        "image4": ""
    },
    {
        "name": "Material",
        "image1": "",
        "image2": "",
        "image3": "",
        "image4": ""
    },
    {
        "name": "Men",
        "image1": "",
        "image2": "",
        "image3": "",
        "image4": ""
    },
    {
        "name": "Minimal",
        "image1": "",
        "image2": "",
        "image3": "",
        "image4": ""
    },
    {
        "name": "Mountain",
        "image1": "",
        "image2": "",
        "image3": "",
        "image4": ""
    },
    {
        "name": "Multi Color",
        "image1": "",
        "image2": "",
        "image3": "",
        "image4": ""
    },
    {
        "name": "Music",
        "image1": "",
        "image2": "",
        "image3": "",
        "image4": ""
    },
    {
        "name": "Nature",
        "image1": "",
        "image2": "",
        "image3": "",
        "image4": ""
    },
    {
        "name": "Neon & Fireworks",
        "image1": "",
        "image2": "",
        "image3": "",
        "image4": ""
    },
    {
        "name": "Ocean",
        "image1": "",
        "image2": "",
        "image3": "",
        "image4": ""
    },
    {
        "name": "Quote",
        "image1": "",
        "image2": "",
        "image3": "",
        "image4": ""
    },
    {
        "name": "Reflection",
        "image1": "",
        "image2": "",
        "image3": "",
        "image4": ""
    },
    {
        "name": "Space",
        "image1": "",
        "image2": "",
        "image3": "",
        "image4": ""
    },
    {
        "name": "Sports",
        "image1": "",
        "image2": "",
        "image3": "",
        "image4": ""
    },
    {
        "name": "Stock",
        "image1": "",
        "image2": "",
        "image3": "",
        "image4": ""
    },
    {
        "name": "Texture",
        "image1": "",
        "image2": "",
        "image3": "",
        "image4": ""
    },
    {
        "name": "Tourism",
        "image1": "",
        "image2": "",
        "image3": "",
        "image4": ""
    },
    {
        "name": "Vehicles",
        "image1": "",
        "image2": "",
        "image3": "",
        "image4": ""
    },
    {
        "name": "Water Drop",
        "image1": "",
        "image2": "",
        "image3": "",
        "image4": ""
    }
]